tinyflask/__init__.py
tinyflask/api.py
tinyflask/middleware.py
tinyflask/response.py
tinyflask-0.0.2.dist-info/METADATA
tinyflask-0.0.2.dist-info/WHEEL
tinyflask-0.0.2.dist-info/top_level.txt
tinyflask-0.0.2.dist-info/RECORD
